pypareto/__init__.py
pypareto/pypareto.py
pypareto-0.3.1.dist-info/licenses/LICENSE
pypareto-0.3.1.dist-info/METADATA
pypareto-0.3.1.dist-info/WHEEL
pypareto-0.3.1.dist-info/top_level.txt
pypareto-0.3.1.dist-info/RECORD
