Metadata-Version: 2.4
Name: pypareto
Version: 0.3.1
Summary: Python library for pareto front extraction
Home-page: https://github.com/kummahiih/pypareto
Author: Pauli Rikula
License: MIT
Classifier: License :: OSI Approved :: MIT License
Classifier: Programming Language :: Python :: 3.6
Requires-Python: ~=3.6
License-File: LICENSE
Dynamic: author
Dynamic: classifier
Dynamic: description
Dynamic: home-page
Dynamic: license
Dynamic: license-file
Dynamic: requires-python
Dynamic: summary
